{
  "topic": "Advent of Europeans and Consolidation of British Power",
  "subtopic": "Education, Trade, and Shipbuilding (18th Century)",
  "flashcards": [
    {
      "id": "fc001",
      "category": "Education",
      "front": "Traditional education focus?",
      "back": "Focused on literature, law, religion, and logic, missing science and technology"
    },
    {
      "id": "fc002",
      "category": "Education",
      "front": "What was missing in traditional education?",
      "back": "Science and technology - focused on literature, law, religion, logic"
    },
    {
      "id": "fc003",
      "category": "Education",
      "front": "Elementary schools types?",
      "back": "Maktabs (Muslim) and Pathshalas (Hindu), mainly for maths, reading, and writing"
    },
    {
      "id": "fc004",
      "category": "Education",
      "front": "What were Maktabs?",
      "back": "Muslim elementary schools for maths, reading, and writing"
    },
    {
      "id": "fc005",
      "category": "Education",
      "front": "What were Pathshalas?",
      "back": "Hindu elementary schools for maths, reading, and writing"
    },
    {
      "id": "fc006",
      "category": "Education",
      "front": "Elementary education subjects?",
      "back": "Mainly maths, reading, and writing (Maktabs and Pathshalas)"
    },
    {
      "id": "fc007",
      "category": "Education",
      "front": "Higher education centres?",
      "back": "Chatuspathis and Tols in Bihar and Bengal, specialising in Sanskrit and Persian"
    },
    {
      "id": "fc008",
      "category": "Education",
      "front": "Where were Chatuspathis and Tols located?",
      "back": "Bihar and Bengal - higher education centres specialising in Sanskrit and Persian"
    },
    {
      "id": "fc009",
      "category": "Education",
      "front": "What did Madrasahs teach?",
      "back": "Arabic and Quranic studies"
    },
    {
      "id": "fc010",
      "category": "Trade & Industry",
      "front": "India's trade balance?",
      "back": "Self-reliance: India was an exporter, balancing trade with gold and silver"
    },
    {
      "id": "fc011",
      "category": "Trade & Industry",
      "front": "India's imports (18th century)?",
      "back": "Pearls, silk, wool, tea, spices, drugs, and gold"
    },
    {
      "id": "fc012",
      "category": "Trade & Industry",
      "front": "India's exports (18th century)?",
      "back": "Cotton textiles, silk, opium, spices, and precious stones"
    },
    {
      "id": "fc013",
      "category": "Trade & Industry",
      "front": "Textile hubs in India?",
      "back": "Dacca, Surat, Patna, Kashmir (woollen products)"
    },
    {
      "id": "fc014",
      "category": "Trade & Industry",
      "front": "Kashmir textile specialty?",
      "back": "Woollen products - textile hub"
    },
    {
      "id": "fc015",
      "category": "Trade & Industry",
      "front": "Dacca known for?",
      "back": "Textile hub along with Surat, Patna, Kashmir"
    },
    {
      "id": "fc016",
      "category": "Navy & Shipbuilding",
      "front": "Shipbuilding prominent regions?",
      "back": "Maharashtra, Andhra, Bengal, and Kerala (Calicut, Quilon)"
    },
    {
      "id": "fc017",
      "category": "Navy & Shipbuilding",
      "front": "Kerala shipbuilding cities?",
      "back": "Calicut, Quilon - shipbuilding prominent in Kerala"
    },
    {
      "id": "fc018",
      "category": "Navy & Shipbuilding",
      "front": "Shivaji's navy purpose?",
      "back": "Countered the Portuguese"
    },
    {
      "id": "fc019",
      "category": "Navy & Shipbuilding",
      "front": "European ships in India?",
      "back": "Often built in India for trade operations"
    }
  ],
  "quizzes": {
    "mcq": [
      {
        "id": "mcq001",
        "question": "What did traditional education focus on?",
        "options": [
          "Science and technology",
          "Literature, law, religion, and logic",
          "Trade and commerce",
          "Military training"
        ],
        "correct": 1,
        "explanation": "Traditional education focused on literature, law, religion, and logic, missing science and technology."
      },
      {
        "id": "mcq002",
        "question": "What was missing in traditional education?",
        "options": [
          "Literature",
          "Religion",
          "Science and technology",
          "Law"
        ],
        "correct": 2,
        "explanation": "Traditional education missed science and technology, focusing on literature, law, religion, and logic."
      },
      {
        "id": "mcq003",
        "question": "What were Maktabs?",
        "options": [
          "Hindu elementary schools",
          "Muslim elementary schools",
          "Higher education centres",
          "Trade schools"
        ],
        "correct": 1,
        "explanation": "Maktabs were Muslim elementary schools for maths, reading, and writing."
      },
      {
        "id": "mcq004",
        "question": "What were Pathshalas?",
        "options": [
          "Muslim elementary schools",
          "Hindu elementary schools",
          "Higher education centres",
          "Textile workshops"
        ],
        "correct": 1,
        "explanation": "Pathshalas were Hindu elementary schools for maths, reading, and writing."
      },
      {
        "id": "mcq005",
        "question": "What subjects did elementary schools teach?",
        "options": [
          "Science and technology",
          "Mainly maths, reading, and writing",
          "Only religious studies",
          "Military training"
        ],
        "correct": 1,
        "explanation": "Elementary schools (Maktabs and Pathshalas) taught mainly maths, reading, and writing."
      },
      {
        "id": "mcq006",
        "question": "Where were Chatuspathis and Tols located?",
        "options": [
          "Maharashtra and Kerala",
          "Bihar and Bengal",
          "Punjab and Sindh",
          "Gujarat and Rajasthan"
        ],
        "correct": 1,
        "explanation": "Chatuspathis and Tols were higher education centres in Bihar and Bengal."
      },
      {
        "id": "mcq007",
        "question": "What did Chatuspathis and Tols specialize in?",
        "options": [
          "Science and mathematics",
          "Sanskrit and Persian",
          "Trade and commerce",
          "Military arts"
        ],
        "correct": 1,
        "explanation": "Chatuspathis and Tols specialized in Sanskrit and Persian."
      },
      {
        "id": "mcq008",
        "question": "What did Madrasahs teach?",
        "options": [
          "Sanskrit and Persian",
          "Science and technology",
          "Arabic and Quranic studies",
          "Trade skills"
        ],
        "correct": 2,
        "explanation": "Madrasahs taught Arabic and Quranic studies."
      },
      {
        "id": "mcq009",
        "question": "What was India's trade position?",
        "options": [
          "Major importer",
          "Self-reliant exporter balancing trade with gold and silver",
          "Dependent on European trade",
          "No international trade"
        ],
        "correct": 1,
        "explanation": "India was self-reliant and an exporter, balancing trade with gold and silver."
      },
      {
        "id": "mcq010",
        "question": "What did India import?",
        "options": [
          "Cotton textiles and opium",
          "Pearls, silk, wool, tea, spices, drugs, and gold",
          "Only food grains",
          "Military equipment"
        ],
        "correct": 1,
        "explanation": "India imported pearls, silk, wool, tea, spices, drugs, and gold."
      },
      {
        "id": "mcq011",
        "question": "What did India export?",
        "options": [
          "Pearls and gold",
          "Cotton textiles, silk, opium, spices, and precious stones",
          "Only agricultural products",
          "Military equipment"
        ],
        "correct": 1,
        "explanation": "India exported cotton textiles, silk, opium, spices, and precious stones."
      },
      {
        "id": "mcq012",
        "question": "Which were major textile hubs?",
        "options": [
          "Delhi, Agra, Lahore",
          "Dacca, Surat, Patna, Kashmir",
          "Bombay, Madras, Calcutta",
          "Hyderabad, Mysore, Travancore"
        ],
        "correct": 1,
        "explanation": "Major textile hubs were Dacca, Surat, Patna, and Kashmir (woollen products)."
      },
      {
        "id": "mcq013",
        "question": "What was Kashmir known for?",
        "options": [
          "Cotton textiles",
          "Woollen products",
          "Silk production",
          "Opium trade"
        ],
        "correct": 1,
        "explanation": "Kashmir was a textile hub known for woollen products."
      },
      {
        "id": "mcq014",
        "question": "Where was shipbuilding prominent?",
        "options": [
          "Only Kerala",
          "Maharashtra, Andhra, Bengal, and Kerala",
          "Only Maharashtra",
          "Punjab and Sindh"
        ],
        "correct": 1,
        "explanation": "Shipbuilding was prominent in Maharashtra, Andhra, Bengal, and Kerala (Calicut, Quilon)."
      },
      {
        "id": "mcq015",
        "question": "Which Kerala cities were known for shipbuilding?",
        "options": [
          "Kochi and Trivandrum",
          "Calicut and Quilon",
          "Kannur and Kollam",
          "Only Calicut"
        ],
        "correct": 1,
        "explanation": "Calicut and Quilon in Kerala were prominent shipbuilding centres."
      },
      {
        "id": "mcq016",
        "question": "What was Shivaji's navy used for?",
        "options": [
          "Trade operations",
          "Countering the Portuguese",
          "Fighting Mughals",
          "Exploration"
        ],
        "correct": 1,
        "explanation": "Shivaji's navy countered the Portuguese."
      },
      {
        "id": "mcq017",
        "question": "Where were European ships often built?",
        "options": [
          "Only in Europe",
          "In India for trade operations",
          "In America",
          "In Africa"
        ],
        "correct": 1,
        "explanation": "European ships were often built in India for trade operations."
      }
    ],
    "comprehensive": [
      {
        "id": "comp001",
        "question": "Analyze the structure and limitations of traditional education in 18th century India, covering elementary schools, higher education centres, and their curricula.",
        "answer": "Traditional Education Focus: Focused on literature, law, religion, and logic. Limitation: Missing science and technology - no systematic scientific education. Implications: While preserving cultural/religious traditions, lack of scientific education meant technological stagnation. Elementary Schools: Maktabs (Muslim) and Pathshalas (Hindu). Subjects: Mainly maths, reading, and writing. Basic literacy and numeracy education. Religious segregation: Different schools for Muslim and Hindu students, reflecting communal educational systems. Higher Education Centres: Chatuspathis and Tols in Bihar and Bengal, specialising in Sanskrit and Persian. Location: Bihar and Bengal - continuing traditional centres of learning. Languages: Sanskrit (Hindu classical/religious texts) and Persian (Mughal administrative language). Madrasahs taught Arabic and Quranic studies - Islamic higher education. Structure: Elementary (Maktabs/Pathshalas: basic skills) \u2192 Higher (Chatuspathis/Tols/Madrasahs: classical languages, religious texts, law). Comprehensive for traditional learning but narrow in scope. Assessment: Strengths: Preserved literary traditions (Sanskrit, Persian, Arabic), religious scholarship, legal knowledge, logical reasoning. Training for administrative/religious roles. Weaknesses: Missing science and technology - no physics, chemistry, biology, engineering, medicine in systematic way. No practical/vocational training emphasized. Limited to elite/religious scholarship. Comparison with Contemporary Europe: 18th century Europe seeing scientific revolution, Enlightenment, technological advances. India's education system preserved traditions but didn't incorporate new scientific knowledge. This educational gap would contribute to technological disadvantage when confronting European colonial powers with superior military technology, industrial capacity. However, traditional education maintained cultural continuity during political fragmentation of 18th century."
      },
      {
        "id": "comp002",
        "question": "Examine India's trade position in the 18th century, including its self-reliance, imports, exports, and major textile hubs.",
        "answer": "Trade Position - Self-reliance: India was an exporter, balancing trade with gold and silver. Significance: Trade surplus - India exported more value than imported, requiring gold/silver imports to balance. Indicates strong manufacturing base (textiles), demand for Indian goods internationally. Self-reliant: Not dependent on imports for essential goods. Imports: Pearls, silk, wool, tea, spices, drugs, and gold. Pattern: Luxury goods (pearls), raw materials (silk, wool), consumables (tea, spices), medicines (drugs), precious metals (gold for balance). India importing spices interesting - while also exporting spices, suggests different varieties/qualities traded. Exports: Cotton textiles, silk, opium, spices, and precious stones. Cotton textiles: Primary export - India's textile industry world-renowned. Silk: Both imported (raw) and exported (finished products). Opium: Significant export - would later become central to British trade with China. Spices: Traditional Indian export. Precious stones: India's gemstone resources. Textile Hubs: Dacca: Famous for muslin - ultra-fine cotton textiles. Surat: Major port and textile manufacturing centre. Patna: Inland textile hub. Kashmir: Woollen products - shawls famous internationally. Regional Specialization: Different regions producing different textile types - cotton (Dacca), wool (Kashmir), general textiles (Surat, Patna). Economic Significance: Strong export economy indicating: 1) Advanced manufacturing (textiles), 2) International market integration, 3) Skilled workforce, 4) Trade surplus attracting gold/silver. This economic strength explains European interest in controlling Indian trade. Textile exports particularly valuable - European demand for Indian cotton textiles high until Industrial Revolution enabled European mechanized production. 18th century India still economically powerful despite political fragmentation - regional states maintained trade networks, manufacturing continued."
      },
      {
        "id": "comp003",
        "question": "Assess India's naval and shipbuilding capabilities in the 18th century, including regional centres, Shivaji's navy, and European dependence on Indian shipbuilding.",
        "answer": "Shipbuilding Regions: Prominent in Maharashtra, Andhra, Bengal, and Kerala (Calicut, Quilon). Regional Distribution: Both western coast (Maharashtra, Kerala) and eastern coast (Andhra, Bengal). Specific Cities: Calicut and Quilon in Kerala - traditional maritime centres. Maharashtra: Maratha territories - connected to Shivaji's navy. Bengal: Major shipbuilding despite being inland-focused state. Andhra: Coastal regions with shipbuilding traditions. Shivaji's Navy: Countered the Portuguese. Context: Marathas under Shivaji (founded empire) developed naval capacity. Purpose: Defense against Portuguese - European naval power threatening Indian coasts. Significance: Indigenous naval development responding to European threat. Shows Maratha state-building included maritime dimension, not just land-based. However, ultimately insufficient to counter European naval supremacy. European Ships Built in India: Often built in India for trade operations. Significance: 1) India had superior shipbuilding technology/materials (teak wood ideal for ships), 2) Cost-effective for Europeans to build locally rather than sail ships from Europe, 3) Indian shipbuilders skilled, 4) European dependence on Indian shipbuilding capabilities. Implications: India possessed maritime technology and infrastructure but didn't translate into naval dominance. Why? European naval powers (Portuguese, Dutch, French, British) had: 1) More advanced naval warfare tactics, 2) Better naval artillery, 3) Centralized naval organization, 4) Global maritime networks. Indian strengths: Shipbuilding technology, multiple coastal centres, indigenous navy (Shivaji). Indian weaknesses: Fragmented states (no unified Indian navy), focus on land-based power, insufficient naval warfare development, regional navies (like Shivaji's) limited in scope. Irony: Europeans building ships in India using Indian technology/labor to establish maritime dominance over India. Pattern: India had economic (trade), technological (shipbuilding), but political fragmentation and lack of naval emphasis allowed European maritime powers to control sea routes, gradually establishing colonial footholds (Goa-Portuguese, later British ports)."
      }
    ]
  }
}